oe2pg/__init__.py
oe2pg/__main__.py
oe2pg/cli.py
oe2pg/connectors/__init__.py
oe2pg/connectors/postgres.py
oe2pg/connectors/progress.py
oe2pg/core/__init__.py
oe2pg/core/config.py
oe2pg/core/exceptions.py
oe2pg/core/mirror.py
oe2pg/managers/__init__.py
oe2pg/managers/checksum.py
oe2pg/managers/cursor.py
oe2pg/managers/display.py
oe2pg/managers/ignore.py
oe2pg/managers/logger.py
oe2pg/managers/tracking.py
oe2pg/models/__init__.py
oe2pg/models/results.py
oe2pg-1.0.0.dist-info/licenses/LICENSE
oe2pg-1.0.0.dist-info/METADATA
oe2pg-1.0.0.dist-info/WHEEL
oe2pg-1.0.0.dist-info/entry_points.txt
oe2pg-1.0.0.dist-info/top_level.txt
oe2pg-1.0.0.dist-info/RECORD
