Metadata-Version: 2.4
Name: oe2pg
Version: 1.0.0
Summary: Ready to use Progress to PostgreSQL database mirroring tool
Home-page: https://github.com/rowingdude/oe2pg
Author: Benjamin Cance
Author-email: canceb@gmail.com
Classifier: Development Status :: 5 - Production/Stable
Classifier: Intended Audience :: System Administrators
Classifier: Intended Audience :: Developers
Classifier: License :: OSI Approved :: MIT License
Classifier: Programming Language :: Python :: 3
Classifier: Programming Language :: Python :: 3.8
Classifier: Programming Language :: Python :: 3.9
Classifier: Programming Language :: Python :: 3.10
Classifier: Programming Language :: Python :: 3.11
Classifier: Topic :: Database
Requires-Python: >=3.8
License-File: LICENSE
Requires-Dist: psycopg2-binary>=2.9.6
Requires-Dist: JayDeBeApi>=1.2.3
Requires-Dist: xxhash>=3.0.0
Dynamic: author
Dynamic: author-email
Dynamic: classifier
Dynamic: description
Dynamic: description-content-type
Dynamic: home-page
Dynamic: license-file
Dynamic: requires-dist
Dynamic: requires-python
Dynamic: summary
